ctbipython
